{  
   "general":{  
      "average":[  
         "critical_hit_accuracy",
         "weapon_accuracy",
         "eliminations_per_life",
         "barrier_damage_done_avg_per_10_min",
         "hero_damage_done_avg_per_10_min",
         "all_damage_done_avg_per_10_min",
         "win_percentage"
      ],
      "cumulative":[  
         "damage_blocked",
         "self_healing",
         "healing_done",
         "eliminations",
         "deaths",
         "final_blows",
         "solo_kills",
         "all_damage_done",
         "objective_kills",
         "critical_hits",
         "hero_damage_done",
         "barrier_damage_done",
         "medals_bronze",
         "medals_silver",
         "medals_gold",
         "medals",
         "cards",
         "games_played",
         "games_won",
         "games_tied",
         "games_lost"
      ],
      "time":[  
         "objective_time",
         "time_spent_on_fire",
         "time_played"
      ],
      "divideByMins":[  
         "damage_blocked",
         "healing_done",
         "all_damage_done",
         "eliminations",
         "deaths"
      ],
      "divideByGames":[  
         "damage_blocked",
         "healing_done",
         "all_damage_done",
         "eliminations",
         "deaths",
         "medals_bronze",
         "medals_silver",
         "medals_gold",
         "medals",
         "cards"
      ],
      "ignoreSessions":[  
         "critical_hit_accuracy",
         "weapon_accuracy",
         "barrier_damage_done_avg_per_10_min",
         "hero_damage_done_avg_per_10_min",
         "all_damage_done_avg_per_10_min",
         "eliminations_per_life",
         "rocket_hammer_melee_accuracy",
         "primal_rage_melee_accuracy",
         "tesla_cannon_accuracy",
         "scoped_accuracy",
         "unscoped_accuracy",
         "hook_accuracy",
         "primary_fire_accuracy"
      ]
   },
   "heroSpecific":{  
      "reaper":[  
         "death_blossom_kills"
      ],
      "tracer":[  
         "pulse_bomb_kills",
         "pulse_bomb_attached"
      ],
      "mercy":[  
         "blaster_kills",
         "players_resurrected",
         "damage_amplified"
      ],
      "hanzo":[  
         "dragonstrike_kills"
      ],
      "torbjörn":[  
         "armor_packs_created",
         "torbjörn_kills",
         "turret_kills",
         "molten_core_kills"
      ],
      "reinhardt":[  
         "charge_kills",
         "fire_strike_kills",
         "earthshatter_kills",
         "rocket_hammer_melee_accuracy"
      ],
      "pharah":[  
         "rocket_direct_hits",
         "barrage_kills"
      ],
      "winston":[  
         "players_knocked_back",
         "jump_pack_kills",
         "primal_rage_kills",
         "primal_rage_melee_accuracy",
         "tesla_cannon_accuracy"
      ],
      "widowmaker":[  
         "venom_mine_kills",
         "scoped_critical_hits",
         "scoped_accuracy"
      ],
      "bastion":[  
         "recon_kills",
         "sentry_kills",
         "tank_kills"
      ],
      "symmetra":[  
         "sentry_turret_kills",
         "players_teleported"
      ],
      "zenyatta":[  
         "transcendence_healing"
      ],
      "genji":[  
         "dragonblade_kills",
         "damage_reflected",
         "deflection_kills"
      ],
      "roadhog":[  
         "enemies_hooked",
         "hooks_attempted",
         "whole_hog_kills",
         "hook_accuracy"
      ],
      "mccree":[  
         "deadeye_kills",
         "fan_the_hammer_kills"
      ],
      "junkrat":[  
         "enemies_trapped",
         "rip-tire_kills",
         "concussion_mine_kills"
      ],
      "zarya":[  
         "graviton_surge_kills",
         "high_energy_kills",
         "projected_barriers_applied",
         "primary_fire_accuracy",
         "average_energy"
      ],
      "soldier:_76":[  
         "helix_rockets_kills",
         "tactical_visor_kills",
         "biotic_fields_deployed",
         "biotic_field_healing_done"
      ],
      "lúcio":[  
         "sound_barriers_provided"
      ],
      "d.va":[  
         "self-destruct_kills",
         "mechs_called",
         "mech_deaths"
      ],
      "mei":[  
         "enemies_frozen",
         "blizzard_kills"
      ],
      "sombra":[  
         "enemies_hacked",
         "enemies_emp'd"
      ],
      "doomfist":[  
         "ability_damage_done",
         "meteor_strike_kills",
         "shields_created"
      ],
      "ana":[  
         "enemies_slept",
         "nano_boosts_applied",
         "nano_boost_assists",
         "biotic_grenade_kills",
         "unscoped_accuracy",
         "scoped_accuracy"
      ],
      "orisa":[  
         "damage_amplified",
         "supercharger_assists"
      ],
      "brigitte":[  
         "armor_provided"
      ],
      "moira":[  
         "coalescence_kills",
         "coalescence_healing"
      ],
      "wrecking_ball":[  
         "players_knocked_back"
      ]
   }
}